MANIFEST.in
README.md
setup.py
explorer/__init__.py
explorer/explorer.py
explorer/configs/GOERLI-stable.json
explorer/configs/KOVAN-stable.json
explorer/configs/MAIN-stable.json
explorer/configs/RINKEBY-stable.json
explorer/configs/ROPSTEN-stable.json
explorer/configs/__init__.py
explorer/enums/__init__.py
explorer/enums/actions_enum.py
explorer/enums/fields_enum.py
explorer/enums/modules_enum.py
explorer/enums/tags_enum.py
explorer/modules/__init__.py
explorer/modules/accounts.py
explorer/modules/blocks.py
explorer/modules/contracts.py
explorer/modules/gastracker.py
explorer/modules/pro.py
explorer/modules/proxy.py
explorer/modules/stats.py
explorer/modules/tokens.py
explorer/modules/transactions.py
explorer/utils/__init__.py
explorer/utils/conversions.py
explorer/utils/parsing.py
python_blockchain_explorer.egg-info/PKG-INFO
python_blockchain_explorer.egg-info/SOURCES.txt
python_blockchain_explorer.egg-info/dependency_links.txt
python_blockchain_explorer.egg-info/not-zip-safe
python_blockchain_explorer.egg-info/requires.txt
python_blockchain_explorer.egg-info/top_level.txt
test/test_modules.py