Metadata-Version: 1.0
Name: python-blockchain-explorer
Version: 1.0.2
Summary: A minimal, yet complete, python API for etherscan.io. arbiscan.io ...
Home-page: https://github.com/orthogonalglobal/python-blockchain-explorer
Author: Dion and Robert
Author-email: UNKNOWN
License: MIT
Platform: UNKNOWN
